TimerLib/__init__.py
TimerLib/async_timer.py
TimerLib/sync_timer.py
TimerLib-5.0.0.dist-info/METADATA
TimerLib-5.0.0.dist-info/WHEEL
TimerLib-5.0.0.dist-info/top_level.txt
TimerLib-5.0.0.dist-info/RECORD
