Metadata-Version: 2.1
Name: TimerLib
Version: 5.0.0
Summary: TimerLib library for synchronous and asynchronous functions
Home-page: https://github.com/Kornil17/TimerLib.git
Author: Kornil17
Author-email: Dimitra4@mail.ru
